flask_activerecord.py
setup.py
Flask_ActiveRecord.egg-info/PKG-INFO
Flask_ActiveRecord.egg-info/SOURCES.txt
Flask_ActiveRecord.egg-info/dependency_links.txt
Flask_ActiveRecord.egg-info/not-zip-safe
Flask_ActiveRecord.egg-info/requires.txt
Flask_ActiveRecord.egg-info/top_level.txt