Metadata-Version: 1.1
Name: Flask-ActiveRecord
Version: 0.2.2
Summary: ActiveRecord support for Flask-SQLAlchemy models
Home-page: https://github.com/kofrasa/flask-activerecord
Author: Francis Asante
Author-email: kofrasa@gmail.com
License: BSD
Platform: any
Classifier: Environment :: Web Environment
Classifier: Intended Audience :: Developers
Classifier: License :: OSI Approved :: BSD License
Classifier: Operating System :: OS Independent
Classifier: Programming Language :: Python
Classifier: Topic :: Internet :: WWW/HTTP :: Dynamic Content
Classifier: Topic :: Software Development :: Libraries :: Python Modules
